poller/__init__.py
poller/poller.py
scheduled_poller/__init__.py
scheduled_poller/poller.py
scheduled_poller/scheduled_poller.py
scheduled_poller-1.3.dist-info/LICENSE
scheduled_poller-1.3.dist-info/METADATA
scheduled_poller-1.3.dist-info/WHEEL
scheduled_poller-1.3.dist-info/top_level.txt
scheduled_poller-1.3.dist-info/RECORD
